blabpy/__init__.py
blabpy/_dev.py
blabpy/blab_data.py
blabpy/cli.py
blabpy/git_utils.py
blabpy/its.py
blabpy/one_time_scripts.py
blabpy/os_utils.py
blabpy/paths.py
blabpy/pipeline.py
blabpy/utils.py
blabpy/validate.py
blabpy/vtc.py
blabpy/wav.py
blabpy/eaf/__init__.py
blabpy/eaf/cli.py
blabpy/eaf/convert.py
blabpy/eaf/eaf_plus.py
blabpy/eaf/eaf_tree.py
blabpy/eaf/eaf_utils.py
blabpy/eaf/etree_utils.py
blabpy/eaf/merge.py
blabpy/ovs/__init__.py
blabpy/ovs/cli.py
blabpy/ovs/paths.py
blabpy/seedlings/__init__.py
blabpy/seedlings/cha.py
blabpy/seedlings/cli.py
blabpy/seedlings/codebooks.py
blabpy/seedlings/gather.py
blabpy/seedlings/io.py
blabpy/seedlings/listened_time.py
blabpy/seedlings/merge.py
blabpy/seedlings/opf.py
blabpy/seedlings/paths.py
blabpy/seedlings/pipeline.py
blabpy/seedlings/scatter.py
blabpy/seedlings/regions/__init__.py
blabpy/seedlings/regions/reformat_seedlings_nouns_regions.py
blabpy/seedlings/regions/regions.py
blabpy/seedlings/regions/top3_top4_surplus.py
blabpy/seedlings/regions/data/regions_special-cases/06_07/regions_processed_amended.csv
blabpy/seedlings/regions/data/regions_special-cases/06_07/regions_processed_original.csv
blabpy/seedlings/regions/data/regions_special-cases/20_12/regions_processed_amended.csv
blabpy/seedlings/regions/data/regions_special-cases/20_12/regions_processed_original.csv
blabpy/seedlings/regions/data/regions_special-cases/22_07/regions_processed_amended.csv
blabpy/seedlings/regions/data/regions_special-cases/22_07/regions_processed_original.csv
blabpy/seedlings/regions/data/regions_special-cases/25_12/regions_processed_amended.csv
blabpy/seedlings/regions/data/regions_special-cases/25_12/regions_processed_original.csv
blabpy/seedlings/sub-recordings_special-cases/Audio_06_17/sub-recordings_amended.csv
blabpy/seedlings/sub-recordings_special-cases/Audio_06_17/sub-recordings_original.csv
blabpy/seedlings/sub-recordings_special-cases/Audio_45_10/sub-recordings_amended.csv
blabpy-0.39.0.dist-info/licenses/LICENSE
blabpy-0.39.0.dist-info/METADATA
blabpy-0.39.0.dist-info/WHEEL
blabpy-0.39.0.dist-info/entry_points.txt
blabpy-0.39.0.dist-info/top_level.txt
blabpy-0.39.0.dist-info/RECORD
